jobspy/__init__.py
jobspy/bayt/__init__.py
jobspy/exception.py
jobspy/glassdoor/__init__.py
jobspy/glassdoor/constant.py
jobspy/glassdoor/util.py
jobspy/google/__init__.py
jobspy/google/constant.py
jobspy/google/util.py
jobspy/indeed/__init__.py
jobspy/indeed/constant.py
jobspy/indeed/util.py
jobspy/linkedin/__init__.py
jobspy/linkedin/constant.py
jobspy/linkedin/util.py
jobspy/model.py
jobspy/util.py
jobspy/ziprecruiter/__init__.py
jobspy/ziprecruiter/constant.py
jobspy/ziprecruiter/util.py
python_jobspy-1.1.78.dist-info/LICENSE
python_jobspy-1.1.78.dist-info/METADATA
python_jobspy-1.1.78.dist-info/WHEEL
python_jobspy-1.1.78.dist-info/RECORD
